cdk_aws_lambda_powertools_layer/__init__.py
cdk_aws_lambda_powertools_layer/py.typed
cdk_aws_lambda_powertools_layer/_jsii/__init__.py
cdk_aws_lambda_powertools_layer/_jsii/cdk-aws-lambda-powertools-layer@3.8.0.jsii.tgz
cdk_aws_lambda_powertools_layer-3.8.0.dist-info/LICENSE
cdk_aws_lambda_powertools_layer-3.8.0.dist-info/METADATA
cdk_aws_lambda_powertools_layer-3.8.0.dist-info/WHEEL
cdk_aws_lambda_powertools_layer-3.8.0.dist-info/top_level.txt
cdk_aws_lambda_powertools_layer-3.8.0.dist-info/RECORD
