Metadata-Version: 2.1
Name: cdk-aws-lambda-powertools-layer
Version: 3.8.0
Summary: Powertools for AWS Lambda layer for python and typescript
Home-page: https://github.com/awslabs/cdk-aws-lambda-powertools-layer.git
Author: Amazon Web Services
License: MIT-0
Project-URL: Source, https://github.com/awslabs/cdk-aws-lambda-powertools-layer.git
Classifier: Intended Audience :: Developers
Classifier: Operating System :: OS Independent
Classifier: Programming Language :: JavaScript
Classifier: Programming Language :: Python :: 3 :: Only
Classifier: Programming Language :: Python :: 3.8
Classifier: Programming Language :: Python :: 3.9
Classifier: Programming Language :: Python :: 3.10
Classifier: Programming Language :: Python :: 3.11
Classifier: Typing :: Typed
Classifier: Development Status :: 5 - Production/Stable
Classifier: License :: OSI Approved
Requires-Python: ~=3.8
License-File: LICENSE
Requires-Dist: aws-cdk-lib <3.0.0,>=2.150.0
Requires-Dist: constructs <11.0.0,>=10.0.5
Requires-Dist: jsii <2.0.0,>=1.101.0
Requires-Dist: publication >=0.0.3
Requires-Dist: typeguard ~=2.13.3
